{
  "video_objs": {
    "woman": [
      "a woman feeds",
      "a woman is feeding",
      "a woman puts",
      "the woman is feeding",
      "a woman gives",
      "a woman handfeeds",
      "a woman seductively feeds"
    ],
    "man": [
      "a man takes",
      "a man",
      "a man s mouth",
      "the man"
    ],
    "food": [
      "food",
      "some food",
      "the food"
    ],
    "hand": [
      "her hand"
    ],
    "fingers": [
      "her fingers",
      "with her fingers"
    ],
    "film": [
      "featuring a film"
    ],
    "movie": [
      "the tamil movie"
    ],
    "boomiga": [
      "boomiga"
    ],
    "vijay": [
      "vijay"
    ],
    "couple": [
      "a couple are eating"
    ],
    "girl": [
      "the girl",
      "a girl"
    ],
    "scene": [
      "a scene"
    ],
    "lover": [
      "his lover"
    ],
    "person": [
      "the person"
    ],
    "lovers": [
      "a lovers are eating"
    ],
    "women": [
      "women giving"
    ],
    "men": [
      "men"
    ]
  }
}